nuclearcraft_designer/__init__.py
nuclearcraft_designer/common/__init__.py
nuclearcraft_designer/common/component.py
nuclearcraft_designer/common/constraints.py
nuclearcraft_designer/common/multi_sequence.py
nuclearcraft_designer/common/placement_rule.py
nuclearcraft_designer/overhauled/__init__.py
nuclearcraft_designer/overhauled/turbine_dynamo_coil/__init__.py
nuclearcraft_designer/overhauled/turbine_dynamo_coil/beta_designer.py
nuclearcraft_designer/overhauled/turbine_dynamo_coil/data_structures.py
nuclearcraft_designer/overhauled/turbine_dynamo_coil/designer.py
nuclearcraft_designer/overhauled/turbine_rotor_blade/__init__.py
nuclearcraft_designer/overhauled/turbine_rotor_blade/beta_designer.py
nuclearcraft_designer/overhauled/turbine_rotor_blade/data_structures.py
nuclearcraft_designer/overhauled/turbine_rotor_blade/designer.py
nuclearcraft_designer/utils/__init__.py
nuclearcraft_designer/utils/optimizer.py
nuclearcraft_designer/utils/scaled_calculator.py
nuclearcraft_designer-0.4.0.dist-info/LICENSE
nuclearcraft_designer-0.4.0.dist-info/METADATA
nuclearcraft_designer-0.4.0.dist-info/WHEEL
nuclearcraft_designer-0.4.0.dist-info/top_level.txt
nuclearcraft_designer-0.4.0.dist-info/RECORD
