Metadata-Version: 2.1
Name: nuclearcraft_designer
Version: 0.4.0
Summary: Generates multiblock designs for NuclearCraft.
Author-email: Celeste Ma <gerry.y.ma@gmail.com>
Project-URL: Homepage, https://github.com/MtCelesteMa/nuclearcraft-designer
Project-URL: Bug Tracker, https://github.com/MtCelesteMa/nuclearcraft-designer/issues
Classifier: Programming Language :: Python :: 3
Classifier: License :: OSI Approved :: MIT License
Classifier: Operating System :: OS Independent
Requires-Python: >=3.10
License-File: LICENSE
